README.rst
setup.py
qconcurrency/__init__.py
qconcurrency/_qbasewindow_.py
qconcurrency/exceptions_.py
qconcurrency/models.py
qconcurrency/testutils.py
qconcurrency/threading.py
qconcurrency.egg-info/PKG-INFO
qconcurrency.egg-info/SOURCES.txt
qconcurrency.egg-info/dependency_links.txt
qconcurrency.egg-info/not-zip-safe
qconcurrency.egg-info/requires.txt
qconcurrency.egg-info/top_level.txt
qconcurrency/widgets/__init__.py
qconcurrency/widgets/_dictmodelqcombobox_.py
qconcurrency/widgets/_dictmodelqmenu_.py
qconcurrency/widgets/_progressbar_.py